{"pageProps":{"posts":[{"title":"LA CTF 2023 – Pycjail","date":"2023-02-12T00:00:00.000Z","draft":false,"authors":["legoclones"],"tags":["LACTF 2023","Misc","Python","Pyjail","Sandbox","Opcode"],"summary":"Use bytecode manipulation to subvert jail restrictions.","canonical":"https://justinapplegate.me/2023/lactf-pycjail","slug":"lactf-2023/pycjail"},{"title":"LA CTF 2023 – Snek","date":"2023-02-12T00:00:00.000Z","draft":false,"authors":["legoclones"],"tags":["LACTF 2023","Reverse","Python","Pickle"],"summary":"Reverse engineer pickle and code objects to determine winning moves.","canonical":"https://justinapplegate.me/2023/lactf-snek","slug":"lactf-2023/snek"},{"title":"Insomni'hack teaser 2022 – ExPiltration","date":"2022-01-30T00:00:00.000Z","draft":false,"authors":["blueset"],"tags":["Insomni'hack teaser 2022","Misc","Python","CV","Video","Binary"],"summary":"Leak data via LED lights.","slug":"insomni-hack-teaser-2022/expiltration"}],"tag":"python"},"__N_SSG":true}